[
  {
    "id": "node/11454810369",
    "name": "Meadow Wood Trail Park",
    "coordinates": [
      -122.3699546,
      40.5144703
    ],
    "category": "leisure",
    "address": "",
    "opening_hours": "",
    "dollar_sign": "$",
    "category_1": "Recreation",
    "category_2": "Scenic viewpoint",
    "description": "A peaceful Park where you can escape the tourist crowds",
    "rarity": "moderately hidden",
    "color": "purple",
    "time": 91,
    "distanceFromRoute": 2.638984680073916,
    "routeProgress": 0.9835830856488931
  },
  {
    "id": "node/358827901",
    "name": "Diamond Spring State Historic Landmark",
    "coordinates": [
      -120.8163245,
      38.6949037
    ],
    "category": "leisure",
    "address": "",
    "opening_hours": "",
    "dollar_sign": "$",
    "category_1": "Recreation",
    "category_2": "Peaceful retreat",
    "description": "A peaceful Park where you can escape the tourist crowds",
    "rarity": "moderately hidden",
    "color": "purple",
    "time": 78,
    "distanceFromRoute": 5.954535451468923,
    "routeProgress": 0.42161330330436997
  },
  {
    "id": "node/358819182",
    "name": "Ridgeway Park",
    "coordinates": [
      -122.3069767,
      40.1466305
    ],
    "category": "leisure",
    "address": "",
    "opening_hours": "",
    "dollar_sign": "$",
    "category_1": "Recreation",
    "category_2": "Scenic viewpoint",
    "description": "Relax and unwind at this local favorite recreation spot",
    "rarity": "moderately hidden",
    "color": "purple",
    "time": 66,
    "distanceFromRoute": 19.80033354222372,
    "routeProgress": 0.9066036060046505
  },
  {
    "id": "node/358827224",
    "name": "Soldiers Memorial Park",
    "coordinates": [
      -120.6315963,
      38.4424102
    ],
    "category": "leisure",
    "address": "",
    "opening_hours": "",
    "dollar_sign": "$",
    "category_1": "Recreation",
    "category_2": "Historical site",
    "description": "Experience authentic local culture at this laid-back spot",
    "rarity": "moderately hidden",
    "color": "purple",
    "time": 62,
    "distanceFromRoute": 4.814311109522216,
    "routeProgress": 0.3481329437035456
  },
  {
    "id": "node/358824588",
    "name": "Palermo Park",
    "coordinates": [
      -121.5441357,
      39.4326654
    ],
    "category": "leisure",
    "address": "",
    "opening_hours": "",
    "dollar_sign": "$",
    "category_1": "Recreation",
    "category_2": "Local favorite",
    "description": "A hidden recreational gem frequented by locals",
    "rarity": "moderately hidden",
    "color": "purple",
    "time": 95,
    "distanceFromRoute": 4.9562272475297995,
    "routeProgress": 0.6637464835961964
  }
]